pocket.py
setup.py
pocket.egg-info/PKG-INFO
pocket.egg-info/SOURCES.txt
pocket.egg-info/dependency_links.txt
pocket.egg-info/requires.txt
pocket.egg-info/top_level.txt
pocket.egg-info/zip-safe