Metadata-Version: 1.0
Name: pocket
Version: 0.3.0
Summary: api wrapper for getpocket.com
Home-page: http://github.com/tapanpandita/pocket/
Author: Tapan Pandita
Author-email: tapan.pandita@gmail.com
License: BSD
Platform: UNKNOWN
